heroku_langchain_aisdk-0.2.1.dist-info/licenses/LICENSE
heroku_mia_sdk/__init__.py
heroku_mia_sdk/agent.py
heroku_mia_sdk/chat.py
heroku_mia_sdk/common.py
heroku_mia_sdk/types.py
heroku_langchain_aisdk-0.2.1.dist-info/METADATA
heroku_langchain_aisdk-0.2.1.dist-info/WHEEL
heroku_langchain_aisdk-0.2.1.dist-info/top_level.txt
heroku_langchain_aisdk-0.2.1.dist-info/RECORD
