Metadata-Version: 2.4
Name: heroku-langchain-aisdk
Version: 0.2.1
Summary: A Python SDK for Heroku's Managed Inference API (MIA), providing easy access to AI models through a LangChain-compatible interface.
Home-page: https://github.com/dsouza-anush/heroku-langchain-aisdk
Author: Heroku
Author-email: Heroku <support@heroku.com>
Maintainer-email: Heroku <support@heroku.com>
License: MIT
Project-URL: Homepage, https://github.com/dsouza-anush/heroku-langchain-aisdk
Project-URL: Documentation, https://github.com/dsouza-anush/heroku-langchain-aisdk#readme
Project-URL: Repository, https://github.com/dsouza-anush/heroku-langchain-aisdk
Project-URL: Bug Tracker, https://github.com/dsouza-anush/heroku-langchain-aisdk/issues
Keywords: heroku,ai,inference,langchain,llm
Classifier: Development Status :: 3 - Alpha
Classifier: Intended Audience :: Developers
Classifier: License :: OSI Approved :: MIT License
Classifier: Programming Language :: Python :: 3
Classifier: Programming Language :: Python :: 3.8
Classifier: Programming Language :: Python :: 3.9
Classifier: Programming Language :: Python :: 3.10
Classifier: Programming Language :: Python :: 3.11
Classifier: Programming Language :: Python :: 3.12
Classifier: Topic :: Software Development :: Libraries :: Python Modules
Classifier: Topic :: Scientific/Engineering :: Artificial Intelligence
Requires-Python: >=3.8
License-File: LICENSE
Requires-Dist: langchain-core>=0.1.0
Requires-Dist: httpx>=0.24.0
Requires-Dist: pydantic>=2.0.0
Provides-Extra: dev
Requires-Dist: pytest>=7.0.0; extra == "dev"
Requires-Dist: pytest-asyncio>=0.21.0; extra == "dev"
Requires-Dist: black>=23.0.0; extra == "dev"
Requires-Dist: isort>=5.12.0; extra == "dev"
Requires-Dist: flake8>=6.0.0; extra == "dev"
Requires-Dist: mypy>=1.0.0; extra == "dev"
Dynamic: author
Dynamic: home-page
Dynamic: license-file
Dynamic: requires-python
